{
    "daily_streaks": {
        "1203505512017035314": {
            "last_claim": "2026-02-11",
            "streak": 1
        }
    },
    "pet_system": {
        "1203505512017035314": {
            "pet": "\ud83d\udc38 Frog",
            "hunger": 100,
            "happiness": 100
        }
    },
    "inventory": {
        "1203505512017035314": [
            "\ud83d\udc51 Crown"
        ]
    },
    "vc_time": {
        "1436734008557047950": {
            "total_minutes": 21.044643133333334
        },
        "849976426647388171": {
            "total_minutes": 17.86650351666667
        },
        "1404113767566016584": {
            "join_time": "2026-02-12T00:32:08.266557"
        },
        "1001175826940829847": {
            "total_minutes": 8.907907183333332,
            "join_time": "2026-02-12T00:14:37.818322"
        },
        "684773505157431347": {
            "total_minutes": 20.072822533333333
        },
        "1111304084646010950": {
            "total_minutes": 7.78299635
        },
        "1041742156395716689": {
            "total_minutes": 38.42619403333333,
            "join_time": "2026-02-12T01:05:51.822195"
        },
        "1203505512017035314": {
            "total_minutes": 3.81669005,
            "join_time": "2026-02-12T00:14:51.706115"
        },
        "1450895604887588877": {
            "total_minutes": 0.8851712166666666
        },
        "1425751662726742078": {
            "total_minutes": 36.099807616666666
        },
        "966965879600472084": {
            "total_minutes": 0,
            "join_time": "2026-02-12T00:28:50.909169"
        },
        "1315355604470206536": {
            "total_minutes": 0
        },
        "1026020583357566976": {
            "total_minutes": 0,
            "join_time": "2026-02-12T00:56:48.142336"
        },
        "1406415749920194591": {
            "total_minutes": 0,
            "join_time": "2026-02-12T00:57:02.357771"
        },
        "396892086328360960": {
            "total_minutes": 0,
            "join_time": "2026-02-12T00:57:46.763616"
        }
    },
    "trivia_scores": {},
    "song_guess_scores": {},
    "last_message_time": {
        "1416777273532616766": "2026-02-11T22:55:05.717949"
    }
}